aiopcloud/__init__.py
aiopcloud/auth.py
aiopcloud/client.py
aiopcloud-0.0.15.dist-info/LICENSE
aiopcloud-0.0.15.dist-info/METADATA
aiopcloud-0.0.15.dist-info/WHEEL
aiopcloud-0.0.15.dist-info/RECORD
