Metadata-Version: 2.3
Name: aiopcloud
Version: 0.0.15
Summary: Async Python client for the pCloud API
License: MIT
Author: honsma235
Author-email: 114189750+honsma235@users.noreply.github.com
Requires-Python: >=3.9
Classifier: License :: OSI Approved :: MIT License
Classifier: Programming Language :: Python :: 3
Classifier: Programming Language :: Python :: 3.9
Classifier: Programming Language :: Python :: 3.10
Classifier: Programming Language :: Python :: 3.11
Classifier: Programming Language :: Python :: 3.12
Classifier: Programming Language :: Python :: 3.13
Requires-Dist: aiohttp (>=3.11.0,<4.0.0)
Project-URL: Bug Tracker, https://github.com/honsma235/aiopcloud/issues
Project-URL: Homepage, https://github.com/honsma235/aiopcloud
Project-URL: Repository, https://github.com/honsma235/aiopcloud
